{
  "_class": "shapePath",
  "booleanOperation": -1,
  "clippingMaskMode": 0,
  "do_objectID": "CB327B46-5798-4D9B-80D7-70670E5EB443",
  "edited": true,
  "exportOptions": {
    "_class": "exportOptions",
    "exportFormats": [
    ],
    "includedLayerIds": [
    ],
    "layerOptions": 0,
    "shouldTrim": false
  },
  "frame": {
    "_class": "rect",
    "constrainProportions": false,
    "height": 4.448275862068968,
    "width": 7.407407407407407,
    "x": 19.25925925925926,
    "y": 38.55172413793103
  },
  "hasClippingMask": false,
  "isClosed": false,
  "isFixedToViewport": false,
  "isFlippedHorizontal": false,
  "isFlippedVertical": false,
  "isLocked": false,
  "isVisible": true,
  "layerListExpandedType": 1,
  "name": "Fill 18",
  "nameIsFixed": false,
  "pointRadiusBehaviour": 1,
  "points": [
    {
      "_class": "curvePoint",
      "cornerRadius": 0,
      "curveFrom": "{0.51823407235666175, 0.69181721572794741}",
      "curveMode": 4,
      "curveTo": "{0.49388977442882503, 0.69181721572794741}",
      "hasCurveFrom": true,
      "hasCurveTo": false,
      "point": "{0.49388977442882503, 0.69181721572794741}"
    },
    {
      "_class": "curvePoint",
      "cornerRadius": 0,
      "curveFrom": "{0.53784475679852961, 0.78002125398512046}",
      "curveMode": 4,
      "curveTo": "{0.53784475679852961, 0.73123369722731923}",
      "hasCurveFrom": false,
      "hasCurveTo": true,
      "point": "{0.53784475679852961, 0.78002125398512046}"
    },
    {
      "_class": "curvePoint",
      "cornerRadius": 0,
      "curveFrom": "{0.53784475679852961, 0.99999999999999756}",
      "curveMode": 1,
      "curveTo": "{0.53784475679852961, 0.99999999999999756}",
      "hasCurveFrom": false,
      "hasCurveTo": false,
      "point": "{0.53784475679852961, 0.99999999999999756}"
    },
    {
      "_class": "curvePoint",
      "cornerRadius": 0,
      "curveFrom": "{0.99999999999999623, 0.44768621389237651}",
      "curveMode": 4,
      "curveTo": "{0.99999999999999623, 0.99999999999999756}",
      "hasCurveFrom": true,
      "hasCurveTo": false,
      "point": "{0.99999999999999623, 0.99999999999999756}"
    },
    {
      "_class": "curvePoint",
      "cornerRadius": 0,
      "curveFrom": "{0.22392889919335296, 0}",
      "curveMode": 2,
      "curveTo": "{0.77602279862821522, 0}",
      "hasCurveFrom": true,
      "hasCurveTo": true,
      "point": "{0.49997584891078439, 0}"
    },
    {
      "_class": "curvePoint",
      "cornerRadius": 0,
      "curveFrom": "{0, 0.99999999999999756}",
      "curveMode": 4,
      "curveTo": "{0, 0.44768621389237651}",
      "hasCurveFrom": false,
      "hasCurveTo": true,
      "point": "{0, 0.99999999999999756}"
    },
    {
      "_class": "curvePoint",
      "cornerRadius": 0,
      "curveFrom": "{0.44983818770226353, 0.99999999999999756}",
      "curveMode": 1,
      "curveTo": "{0.44983818770226353, 0.99999999999999756}",
      "hasCurveFrom": false,
      "hasCurveTo": false,
      "point": "{0.44983818770226353, 0.99999999999999756}"
    },
    {
      "_class": "curvePoint",
      "cornerRadius": 0,
      "curveFrom": "{0.44983818770226353, 0.73123369722731923}",
      "curveMode": 4,
      "curveTo": "{0.44983818770226353, 0.78002125398512046}",
      "hasCurveFrom": true,
      "hasCurveTo": false,
      "point": "{0.44983818770226353, 0.78002125398512046}"
    },
    {
      "_class": "curvePoint",
      "cornerRadius": 0,
      "curveFrom": "{0.49388977442882503, 0.69181721572794741}",
      "curveMode": 4,
      "curveTo": "{0.46954547650098832, 0.69181721572794741}",
      "hasCurveFrom": false,
      "hasCurveTo": true,
      "point": "{0.49388977442882503, 0.69181721572794741}"
    }
  ],
  "resizingConstraint": 63,
  "resizingType": 0,
  "rotation": 0,
  "shouldBreakMaskChain": false,
  "style": {
    "_class": "style",
    "blur": {
      "_class": "blur",
      "center": "{0.5, 0.5}",
      "isEnabled": false,
      "motionAngle": 0,
      "radius": 14.81481481481481,
      "saturation": 1,
      "type": 0
    },
    "endMarkerType": 0,
    "fills": [
      {
        "_class": "fill",
        "color": {
          "_class": "color",
          "alpha": 1,
          "blue": 0.475,
          "green": 0.424,
          "red": 0.843
        },
        "fillType": 0,
        "isEnabled": true,
        "noiseIndex": 0,
        "noiseIntensity": 0,
        "patternFillType": 1,
        "patternTileScale": 1
      }
    ],
    "miterLimit": 10,
    "startMarkerType": 0,
    "windingRule": 1
  }
}