{
  "_class": "shapePath",
  "booleanOperation": 1,
  "clippingMaskMode": 0,
  "do_objectID": "50FC5586-FA4D-4479-8766-9A75DCCF3D21",
  "edited": true,
  "exportOptions": {
    "_class": "exportOptions",
    "exportFormats": [
    ],
    "includedLayerIds": [
    ],
    "layerOptions": 0,
    "shouldTrim": false
  },
  "frame": {
    "_class": "rect",
    "constrainProportions": false,
    "height": 4.542294322132096,
    "width": 60.23842592592592,
    "x": 212.5393518518518,
    "y": 978.8644264194667
  },
  "hasClippingMask": false,
  "isClosed": true,
  "isFixedToViewport": false,
  "isFlippedHorizontal": false,
  "isFlippedVertical": false,
  "isLocked": false,
  "isVisible": true,
  "layerListExpandedType": 0,
  "name": "bottom",
  "nameIsFixed": true,
  "pointRadiusBehaviour": 0,
  "points": [
    {
      "_class": "curvePoint",
      "cornerRadius": 0,
      "curveFrom": "{0.12896187146653404, 0.00049165100179493493}",
      "curveMode": 1,
      "curveTo": "{0.13207547169811321, 0}",
      "hasCurveFrom": true,
      "hasCurveTo": false,
      "point": "{0.13207547169811321, 0}"
    },
    {
      "_class": "curvePoint",
      "cornerRadius": 0,
      "curveFrom": "{0.054908474081132315, 0}",
      "curveMode": 3,
      "curveTo": "{0.12581577352736953, 0}",
      "hasCurveFrom": true,
      "hasCurveTo": true,
      "point": "{0.12264150943396226, 0}"
    },
    {
      "_class": "curvePoint",
      "cornerRadius": 0,
      "curveFrom": "{0, 0.77614237489999027}",
      "curveMode": 2,
      "curveTo": "{0, 0.22385762510000973}",
      "hasCurveFrom": true,
      "hasCurveTo": true,
      "point": "{0, 0.5}"
    },
    {
      "_class": "curvePoint",
      "cornerRadius": 0,
      "curveFrom": "{0.12581577352737008, 1}",
      "curveMode": 3,
      "curveTo": "{0.054908474081132315, 1}",
      "hasCurveFrom": true,
      "hasCurveTo": true,
      "point": "{0.12264150943396226, 1}"
    },
    {
      "_class": "curvePoint",
      "cornerRadius": 0,
      "curveFrom": "{0.13207547169811856, 0.99854270640435061}",
      "curveMode": 4,
      "curveTo": "{0.12896187146653512, 0.99950834899820507}",
      "hasCurveFrom": false,
      "hasCurveTo": true,
      "point": "{0.13207547169811856, 0.99854270640435061}"
    },
    {
      "_class": "curvePoint",
      "cornerRadius": 0,
      "curveFrom": "{0.95011743122803027, 0.97890328841663177}",
      "curveMode": 1,
      "curveTo": "{0.8867924528301887, 1}",
      "hasCurveFrom": true,
      "hasCurveTo": false,
      "point": "{0.8867924528301887, 1}"
    },
    {
      "_class": "curvePoint",
      "cornerRadius": 0,
      "curveFrom": "{1, 0.23679885563467451}",
      "curveMode": 2,
      "curveTo": "{1, 0.76320114436532549}",
      "hasCurveFrom": true,
      "hasCurveTo": true,
      "point": "{1, 0.5}"
    },
    {
      "_class": "curvePoint",
      "cornerRadius": 0,
      "curveFrom": "{0.88679245283019459, 0.0014572935956493893}",
      "curveMode": 4,
      "curveTo": "{0.95011743122803027, 0.021096711583368233}",
      "hasCurveFrom": false,
      "hasCurveTo": true,
      "point": "{0.88679245283019459, 0.0014572935956493893}"
    }
  ],
  "resizingConstraint": 63,
  "resizingType": 0,
  "rotation": 0,
  "shouldBreakMaskChain": false,
  "style": {
    "_class": "style",
    "blur": {
      "_class": "blur",
      "center": "{0.5, 0.5}",
      "isEnabled": false,
      "motionAngle": 0,
      "radius": 11.35573580533024,
      "saturation": 1,
      "type": 0
    },
    "borders": [
      {
        "_class": "border",
        "color": {
          "_class": "color",
          "alpha": 1,
          "blue": 0.592,
          "green": 0.592,
          "red": 0.592
        },
        "fillType": 0,
        "isEnabled": false,
        "position": 1,
        "thickness": 1.135573580533024
      }
    ],
    "endMarkerType": 0,
    "fills": [
      {
        "_class": "fill",
        "color": {
          "_class": "color",
          "alpha": 1,
          "blue": 0.2705882352941176,
          "green": 0.2705882352941176,
          "red": 0.2705882352941176
        },
        "fillType": 1,
        "gradient": {
          "_class": "gradient",
          "elipseLength": 0,
          "from": "{3.061616997868383e-17, 0.5}",
          "gradientType": 0,
          "stops": [
            {
              "_class": "gradientStop",
              "color": {
                "_class": "color",
                "alpha": 1,
                "blue": 0.8486926020408163,
                "green": 0.828270043319569,
                "red": 0.8104003044384775
              },
              "position": 0
            },
            {
              "_class": "gradientStop",
              "color": {
                "_class": "color",
                "alpha": 1,
                "blue": 0.9411764705882353,
                "green": 0.9294117647058824,
                "red": 0.9254901960784314
              },
              "position": 0.1257638685597189
            },
            {
              "_class": "gradientStop",
              "color": {
                "_class": "color",
                "alpha": 1,
                "blue": 0.9490196078431372,
                "green": 0.9450980392156862,
                "red": 0.9411764705882353
              },
              "position": 0.9334153615339575
            },
            {
              "_class": "gradientStop",
              "color": {
                "_class": "color",
                "alpha": 1,
                "blue": 1,
                "green": 0.996078431372549,
                "red": 0.984313725490196
              },
              "position": 1
            }
          ],
          "to": "{1, 0.5}"
        },
        "isEnabled": true,
        "noiseIndex": 0,
        "noiseIntensity": 0,
        "patternFillType": 0,
        "patternTileScale": 1
      },
      {
        "_class": "fill",
        "color": {
          "_class": "color",
          "alpha": 1,
          "blue": 0.847,
          "green": 0.847,
          "red": 0.847
        },
        "fillType": 1,
        "gradient": {
          "_class": "gradient",
          "elipseLength": 0,
          "from": "{0.5, 0.80193999855156428}",
          "gradientType": 0,
          "stops": [
            {
              "_class": "gradientStop",
              "color": {
                "_class": "color",
                "alpha": 0.5,
                "blue": 1,
                "green": 1,
                "red": 1
              },
              "position": 0
            },
            {
              "_class": "gradientStop",
              "color": {
                "_class": "color",
                "alpha": 1,
                "blue": 0.8547512755102041,
                "green": 0.8342091769458139,
                "red": 0.815949533777467
              },
              "position": 1
            }
          ],
          "to": "{0.5, 1}"
        },
        "isEnabled": true,
        "noiseIndex": 0,
        "noiseIntensity": 0,
        "patternFillType": 1,
        "patternTileScale": 1
      }
    ],
    "innerShadows": [
      {
        "_class": "innerShadow",
        "blurRadius": 3,
        "color": {
          "_class": "color",
          "alpha": 0.1,
          "blue": 0,
          "green": 0,
          "red": 0
        },
        "contextSettings": {
          "_class": "graphicsContextSettings",
          "blendMode": 2,
          "opacity": 1
        },
        "isEnabled": true,
        "offsetX": 0,
        "offsetY": 0,
        "spread": 1
      },
      {
        "_class": "innerShadow",
        "blurRadius": 0,
        "color": {
          "_class": "color",
          "alpha": 0.2,
          "blue": 0,
          "green": 0,
          "red": 0
        },
        "contextSettings": {
          "_class": "graphicsContextSettings",
          "blendMode": 8,
          "opacity": 1
        },
        "isEnabled": true,
        "offsetX": 0,
        "offsetY": 0,
        "spread": 1
      }
    ],
    "miterLimit": 10,
    "startMarkerType": 0,
    "windingRule": 1
  }
}