{
  "_class": "shapePath",
  "booleanOperation": -1,
  "clippingMaskMode": 0,
  "do_objectID": "D738FF8F-CF26-4D46-BDAC-B106A638C76A",
  "edited": true,
  "exportOptions": {
    "_class": "exportOptions",
    "exportFormats": [
    ],
    "includedLayerIds": [
    ],
    "layerOptions": 0,
    "shouldTrim": false
  },
  "frame": {
    "_class": "rect",
    "constrainProportions": false,
    "height": 9.795351731944109,
    "width": 13.22900000000001,
    "x": 167.5888,
    "y": 181.6334
  },
  "hasClippingMask": false,
  "isClosed": false,
  "isFixedToViewport": false,
  "isFlippedHorizontal": false,
  "isFlippedVertical": false,
  "isLocked": false,
  "isVisible": true,
  "layerListExpandedType": 1,
  "name": "Fill 68",
  "nameIsFixed": false,
  "pointRadiusBehaviour": 1,
  "points": [
    {
      "_class": "curvePoint",
      "cornerRadius": 0,
      "curveFrom": "{1, 0}",
      "curveMode": 1,
      "curveTo": "{1, 0}",
      "hasCurveFrom": false,
      "hasCurveTo": false,
      "point": "{1, 0}"
    },
    {
      "_class": "curvePoint",
      "cornerRadius": 0,
      "curveFrom": "{0.83384987527401877, 0}",
      "curveMode": 1,
      "curveTo": "{0.83384987527401877, 0}",
      "hasCurveFrom": false,
      "hasCurveTo": false,
      "point": "{0.83384987527401877, 0}"
    },
    {
      "_class": "curvePoint",
      "cornerRadius": 0,
      "curveFrom": "{0.68138181268425435, 0.82324761996060736}",
      "curveMode": 4,
      "curveTo": "{0.76717816917378412, 0.52279899080087699}",
      "hasCurveFrom": true,
      "hasCurveTo": false,
      "point": "{0.76717816917378412, 0.52279899080087699}"
    },
    {
      "_class": "curvePoint",
      "cornerRadius": 0,
      "curveFrom": "{0.014060019653791432, 0.39038924835433542}",
      "curveMode": 4,
      "curveTo": "{0.43268576611988907, 0.75464365163055702}",
      "hasCurveFrom": true,
      "hasCurveTo": true,
      "point": "{0.021165620984201439, 0.31463903332323812}"
    },
    {
      "_class": "curvePoint",
      "cornerRadius": 0,
      "curveFrom": "{0, 0.54158341070077154}",
      "curveMode": 4,
      "curveTo": "{0.0071056013304121564, 0.46593528490826042}",
      "hasCurveFrom": false,
      "hasCurveTo": true,
      "point": "{0, 0.54158341070077154}"
    },
    {
      "_class": "curvePoint",
      "cornerRadius": 0,
      "curveFrom": "{0.78305238491193574, 1.052642139064214}",
      "curveMode": 4,
      "curveTo": "{0.54289817824476594, 0.90839004494165188}",
      "hasCurveFrom": true,
      "hasCurveTo": false,
      "point": "{0.54289817824476594, 0.90839004494165188}"
    },
    {
      "_class": "curvePoint",
      "cornerRadius": 0,
      "curveFrom": "{0.96507672537606859, 0.55332367313820596}",
      "curveMode": 4,
      "curveTo": "{0.91957064026003543, 1.0265072939860995}",
      "hasCurveFrom": true,
      "hasCurveTo": true,
      "point": "{0.95267971879960656, 0.83018968818448124}"
    },
    {
      "_class": "curvePoint",
      "cornerRadius": 0,
      "curveFrom": "{1, 0}",
      "curveMode": 4,
      "curveTo": "{0.98072416660367412, 0.2767639258076891}",
      "hasCurveFrom": false,
      "hasCurveTo": true,
      "point": "{1, 0}"
    }
  ],
  "resizingConstraint": 63,
  "resizingType": 0,
  "rotation": 0,
  "shouldBreakMaskChain": false,
  "style": {
    "_class": "style",
    "endMarkerType": 0,
    "fills": [
      {
        "_class": "fill",
        "color": {
          "_class": "color",
          "alpha": 1,
          "blue": 0.094,
          "green": 0.02,
          "red": 0.78
        },
        "fillType": 0,
        "isEnabled": true,
        "noiseIndex": 0,
        "noiseIntensity": 0,
        "patternFillType": 1,
        "patternTileScale": 1
      }
    ],
    "miterLimit": 10,
    "startMarkerType": 0,
    "windingRule": 1
  }
}