{
  "_class": "shapePath",
  "booleanOperation": -1,
  "clippingMaskMode": 0,
  "do_objectID": "FEE49EDC-1259-4462-856B-459C1259D5DE",
  "edited": true,
  "exportOptions": {
    "_class": "exportOptions",
    "exportFormats": [
    ],
    "includedLayerIds": [
    ],
    "layerOptions": 0,
    "shouldTrim": false
  },
  "frame": {
    "_class": "rect",
    "constrainProportions": false,
    "height": 1.29708837890625,
    "width": 1.297264160156251,
    "x": 6.972443349609375,
    "y": 6.71728109549181
  },
  "hasClippingMask": false,
  "isClosed": true,
  "isFixedToViewport": false,
  "isFlippedHorizontal": false,
  "isFlippedVertical": false,
  "isLocked": false,
  "isVisible": true,
  "layerListExpandedType": 0,
  "name": "Path",
  "nameIsFixed": false,
  "pointRadiusBehaviour": 1,
  "points": [
    {
      "_class": "curvePoint",
      "cornerRadius": 0,
      "curveFrom": "{0.76054652274901002, 1}",
      "curveMode": 1,
      "curveTo": "{0.76054652274901002, 1}",
      "hasCurveFrom": false,
      "hasCurveTo": false,
      "point": "{0.76054652274901002, 1}"
    },
    {
      "_class": "curvePoint",
      "cornerRadius": 0,
      "curveFrom": "{1, 0.75938473978490739}",
      "curveMode": 1,
      "curveTo": "{1, 0.75938473978490739}",
      "hasCurveFrom": false,
      "hasCurveTo": false,
      "point": "{1, 0.75938473978490739}"
    },
    {
      "_class": "curvePoint",
      "cornerRadius": 0,
      "curveFrom": "{0.24060524006915066, 0}",
      "curveMode": 1,
      "curveTo": "{0.24060524006915066, 0}",
      "hasCurveFrom": false,
      "hasCurveTo": false,
      "point": "{0.24060524006915066, 0}"
    },
    {
      "_class": "curvePoint",
      "cornerRadius": 0,
      "curveFrom": "{0, 0.23944075466498935}",
      "curveMode": 1,
      "curveTo": "{0, 0.23944075466498935}",
      "hasCurveFrom": false,
      "hasCurveTo": false,
      "point": "{0, 0.23944075466498935}"
    },
    {
      "_class": "curvePoint",
      "cornerRadius": 0,
      "curveFrom": "{0.76054652274901002, 1}",
      "curveMode": 1,
      "curveTo": "{0.76054652274901002, 1}",
      "hasCurveFrom": false,
      "hasCurveTo": false,
      "point": "{0.76054652274901002, 1}"
    }
  ],
  "resizingConstraint": 63,
  "resizingType": 0,
  "rotation": 0,
  "shouldBreakMaskChain": false,
  "style": {
    "_class": "style",
    "blur": {
      "_class": "blur",
      "center": "{0.5, 0.5}",
      "isEnabled": false,
      "motionAngle": 0,
      "radius": 0.29296875,
      "saturation": 1,
      "type": 0
    },
    "endMarkerType": 0,
    "fills": [
      {
        "_class": "fill",
        "color": {
          "_class": "color",
          "alpha": 1,
          "blue": 0.3019607843137255,
          "green": 0.3215686274509804,
          "red": 0.8666666666666667
        },
        "fillType": 0,
        "isEnabled": true,
        "noiseIndex": 0,
        "noiseIntensity": 0,
        "patternFillType": 1,
        "patternTileScale": 1
      }
    ],
    "miterLimit": 10,
    "startMarkerType": 0,
    "windingRule": 0
  }
}